fileo.py
src/__init__.py
src/core/app_globals.py
src/core/app_signals.py
src/core/bk_ut.py
src/core/check_update.py
src/core/compact_list.py
src/core/create_db.py
src/core/db_ut.py
src/core/dir_model.py
src/core/drag_drop.py
src/core/file_model.py
src/core/filename_editor.py
src/core/history.py
src/core/linux_menu.py
src/core/load_files.py
src/core/low_bk.py
src/core/reports.py
src/core/sho.py
src/core/utils.py
src/core/win_menu.py
src/core/win_win.py
src/main.py
src/qss/__init__.py
src/qss/angle_down.svg
src/qss/angle_right.svg
src/qss/app.ico
src/qss/creation.svg
src/qss/default.param
src/qss/default.qss
src/qss/fileo.toml
src/qss/icons.toml
src/qss/vline3.svg
src/tug/__init__.py
src/ui/main.ui
src/ui/ui_main.py
src/widgets/about.py
src/widgets/custom_grips.py
src/widgets/file_authors.py
src/widgets/file_data.py
src/widgets/file_info.py
src/widgets/file_note.py
src/widgets/file_note.ui
src/widgets/file_notes.py
src/widgets/file_tags.py
src/widgets/filter_setup.py
src/widgets/find_files.py
src/widgets/fold_container.py
src/widgets/fold_container.ui
src/widgets/foldable.py
src/widgets/foldable.ui
src/widgets/locations.py
src/widgets/note_editor.py
src/widgets/notes.ui
src/widgets/open_db.py
src/widgets/open_db.ui
src/widgets/preferences.py
src/widgets/scan_disk.ui
src/widgets/scan_disk_for_files.py
src/widgets/set_filter.ui
src/widgets/ui_file_note.py
src/widgets/ui_fold_container.py
src/widgets/ui_foldable.py
src/widgets/ui_notes.py
src/widgets/ui_open_db.py
src/widgets/ui_scan_disk.py
src/widgets/ui_set_filter.py
src/widgets/workers.py
md4_fileo-1.1.4.dist-info/LICENSE
md4_fileo-1.1.4.dist-info/METADATA
md4_fileo-1.1.4.dist-info/WHEEL
md4_fileo-1.1.4.dist-info/RECORD
