Metadata-Version: 2.1
Name: md4-fileo
Version: 1.1.4
Summary: Yet another file organizer
Home-page: https://github.com/Michal-D4/fileo
Author: mihal.d44
Author-email: mihal.d44@gmail.com
Requires-Python: >=3.10,<4.0
Classifier: Programming Language :: Python :: 3
Classifier: Programming Language :: Python :: 3.10
Classifier: Programming Language :: Python :: 3.11
Requires-Dist: apsw (>=3.40.1.0,<4.0.0.0)
Requires-Dist: loguru (>=0.6.0,<0.7.0)
Requires-Dist: pypdf2 (>=3.0.1,<4.0.0)
Requires-Dist: pyqt6 (>=6.4.0,<7.0.0)
Project-URL: Repository, https://github.com/Michal-D4/fileo
